synopy/__init__.py
synopy/api.py
synopy/base.py
synopy/errors.py
synopy-0.0.0.post1.dist-info/LICENSE
synopy-0.0.0.post1.dist-info/METADATA
synopy-0.0.0.post1.dist-info/WHEEL
synopy-0.0.0.post1.dist-info/top_level.txt
synopy-0.0.0.post1.dist-info/RECORD
