Metadata-Version: 2.1
Name: synopy
Version: 0.0.0.post1
Summary: Python library for the Synology DiskStation APIs
Home-page: https://github.com/graingert/synopy
Author: George Spanos
Author-email: spanosgeorge@gmail.com
Maintainer: Thomas Grainger
Maintainer-email: synopy@graingert.co.uk
License: MIT
Platform: UNKNOWN
Requires-Dist: requests (<3.0.0,>=2)
Requires-Dist: six (<2.0.0,>=1)
